{"stat.pickup.minecraft.bone":3,"stat.killEntity.EntityHorse":1,"stat.horseOneCm":587,"stat.leaveGame":16,"stat.mineBlock.minecraft.cobblestone":19,"stat.pickup.minecraft.stone_pickaxe":2,"stat.pickup.minecraft.flint":2,"stat.mineBlock.minecraft.brown_mushroom":1,"stat.useItem.minecraft.mutton":3,"stat.swimOneCm":71480,"stat.climbOneCm":633,"stat.mineBlock.minecraft.web":5,"achievement.buildWorkBench":2,"stat.pickup.minecraft.porkchop":5,"stat.enderchestOpened":1,"stat.useItem.minecraft.dirt":23,"achievement.exploreAllBiomes":{"value":0,"progress":["ForestHills","Roofed Forest","Plains","TaigaHills","The End","Beach","Stone Beach","Extreme Hills+","Forest","River","Ocean","Taiga","Extreme Hills","Swampland","Deep Ocean"]},"stat.mineBlock.minecraft.stone_brick_stairs":2,"stat.pickup.minecraft.rotten_flesh":8,"stat.pickup.minecraft.sand":31,"stat.craftItem.minecraft.spruce_boat":4,"stat.useItem.minecraft.birch_boat":8,"stat.craftItem.minecraft.stone_pickaxe":1,"stat.pickup.minecraft.cobblestone":386,"stat.flyOneCm":741427,"stat.mineBlock.minecraft.sand":31,"stat.pickup.minecraft.acacia_boat":2,"stat.mineBlock.minecraft.iron_ore":8,"stat.timeSinceDeath":8085,"stat.pickup.minecraft.mutton":5,"stat.pickup.minecraft.double_plant":5,"stat.trappedChestTriggered":1,"stat.pickup.minecraft.dark_oak_door":1,"stat.pickup.minecraft.stonebrick":9,"stat.furnaceInteraction":1,"stat.killEntity.Wolf":1,"stat.mineBlock.minecraft.dark_oak_stairs":3,"stat.useItem.minecraft.dark_oak_stairs":5,"stat.mineBlock.minecraft.coal_ore":7,"stat.talkedToVillager":1,"stat.pickup.minecraft.wooden_sword":1,"stat.pickup.minecraft.string":16,"stat.pickup.minecraft.beef":4,"stat.pickup.minecraft.furnace":2,"stat.entityKilledBy.Skeleton":1,"stat.useItem.minecraft.written_book":1,"achievement.mineWood":18,"stat.sprintOneCm":361257,"stat.useItem.minecraft.stone_stairs":8,"stat.useItem.minecraft.dark_oak_door":1,"stat.useItem.minecraft.bed":1,"achievement.openInventory":80,"stat.pickup.minecraft.stone_stairs":12,"stat.useItem.minecraft.wheat_seeds":279,"stat.mineBlock.minecraft.crafting_table":1,"stat.useItem.minecraft.carrot":116,"stat.deaths":10,"stat.mineBlock.minecraft.planks":2,"stat.drop":3,"stat.playOneMinute":162207,"stat.killEntity.Sheep":3,"stat.killEntity.Zombie":4,"stat.mineBlock.minecraft.tallgrass":15,"stat.diveOneCm":110570,"stat.pickup.minecraft.wheat":164,"stat.chestOpened":10,"stat.useItem.minecraft.stone":31,"stat.pickup.minecraft.gravel":14,"stat.pickup.minecraft.arrow":2,"stat.pickup.minecraft.stone_axe":2,"stat.useItem.minecraft.porkchop":2,"stat.useItem.minecraft.rotten_flesh":1,"stat.pickup.minecraft.stone_brick_stairs":2,"stat.jump":2156,"stat.useItem.minecraft.sand":8,"stat.pickup.minecraft.coal":60,"stat.fallOneCm":107744,"stat.craftItem.minecraft.birch_boat":8,"stat.pickup.minecraft.carrot":245,"stat.useItem.minecraft.stone_axe":42,"stat.drop.minecraft.stone_sword":1,"stat.crouchOneCm":17508,"stat.pickup.minecraft.spider_eye":2,"stat.pickup.minecraft.dirt":128,"stat.craftingTableInteraction":3,"stat.pickup.minecraft.iron_ore":16,"stat.boatOneCm":885521,"stat.useItem.minecraft.sapling":28,"stat.drop.minecraft.acacia_boat":1,"stat.mineBlock.minecraft.leaves2":1,"stat.pickup.minecraft.wooden_pickaxe":1,"stat.mineBlock.minecraft.stone_stairs":12,"stat.damageTaken":3694,"stat.useItem.minecraft.stone_brick_stairs":2,"stat.pickup.minecraft.written_book":1,"stat.useItem.minecraft.wooden_pickaxe":4,"stat.pickup.minecraft.birch_boat":9,"stat.pickup.minecraft.dye":2,"stat.pickup.minecraft.planks":46,"stat.pickup.minecraft.bed":2,"stat.pickup.minecraft.wheat_seeds":286,"stat.pickup.minecraft.potato":198,"stat.mineBlock.minecraft.gravel":2,"stat.useItem.minecraft.stone_pickaxe":226,"stat.useItem.minecraft.stone_sword":116,"stat.damageDealt":2980,"stat.killEntity.Rabbit":1,"stat.killEntity.Cow":1,"stat.mineBlock.minecraft.dirt":59,"stat.useItem.minecraft.crafting_table":2,"stat.killEntity.Pig":1,"stat.pickup.minecraft.boat":12,"stat.walkOneCm":325104,"stat.playerKills":3,"stat.pickup.minecraft.stick":4,"stat.drop.minecraft.rotten_flesh":1,"stat.pickup.minecraft.crafting_table":3,"stat.useItem.minecraft.cobblestone":744,"stat.craftItem.minecraft.crafting_table":1,"stat.useItem.minecraft.gravel":6,"stat.mineBlock.minecraft.double_plant":3,"stat.useItem.minecraft.spruce_boat":4,"stat.breakItem.minecraft.stone_pickaxe":2,"stat.craftItem.minecraft.boat":8,"stat.pickup.minecraft.log":21,"stat.pickup.minecraft.stone":442,"stat.pickup.minecraft.tipped_arrow":1,"stat.pickup.minecraft.sapling":2,"stat.mineBlock.minecraft.stonebrick":9,"stat.craftItem.minecraft.planks":84,"stat.useItem.minecraft.acacia_boat":1,"stat.killEntity.Spider":1,"stat.pickup.minecraft.stone_sword":3,"stat.pickup.minecraft.dark_oak_stairs":5,"stat.mobKills":13,"stat.useItem.minecraft.stonebrick":9,"stat.mineBlock.minecraft.log":19,"stat.useItem.minecraft.boat":2,"stat.mineBlock.minecraft.leaves":3,"stat.pickup.minecraft.torch":3,"stat.sneakTime":7529,"stat.pickup.minecraft.wool":6,"stat.pickup.minecraft.rabbit_stew":4,"stat.mineBlock.minecraft.stone":148}