{"stat.walkOneCm":37616,"stat.pickup.minecraft.bone":1,"stat.killEntity.EntityHorse":1,"achievement.openInventory":2,"stat.killEntity.Chicken":3,"stat.leaveGame":1,"stat.pickup.minecraft.feather":2,"stat.damageTaken":40,"stat.pickup.minecraft.stone_sword":1,"stat.mobKills":4,"stat.mineBlock.minecraft.log":12,"stat.pickup.minecraft.log":12,"stat.flyOneCm":5799,"stat.drop":1,"stat.swimOneCm":3112,"stat.jump":119,"stat.playOneMinute":7263,"stat.fallOneCm":888,"stat.useItem.minecraft.stone_pickaxe":9,"stat.drop.minecraft.stone_sword":1,"stat.useItem.minecraft.stone_axe":22,"stat.damageDealt":354,"stat.pickup.minecraft.chicken":3,"stat.timeSinceDeath":7263,"achievement.mineWood":10,"stat.sprintOneCm":39280,"achievement.exploreAllBiomes":{"value":0,"progress":["ForestHills","Extreme Hills+","Forest","River","Plains","Extreme Hills"]},"stat.mineBlock.minecraft.tallgrass":5,"stat.diveOneCm":954}